sgenet.py
sgenet-0.2.dist-info/LICENSE
sgenet-0.2.dist-info/METADATA
sgenet-0.2.dist-info/WHEEL
sgenet-0.2.dist-info/top_level.txt
sgenet-0.2.dist-info/RECORD
