Metadata-Version: 2.1
Name: sgenet
Version: 0.2
Summary: Python package for spelling and grammar correction
Home-page: https://github.com/akshat4112/sgenet
Author: Akshat Gupta
Author-email: akshat41121995@gmail.com
License: UNKNOWN
Platform: UNKNOWN
